Workbook

Sheet Risk Assessment Data
A1: Risk ID | B1: Risk Description | C1: Likelihood | D1: Impact | E1: Likelihood-Impact
A2: 1 | B2: Engineer Steals Trading Algorithms from Technology Database | C2: 10 | D2: 40 | E2: =_xlfn.CONCAT(OFFSET($A$1,ROW()-1,COLUMN()-3),OFFSET($A$1,ROW()-1,COLUMN()-2)) -> 1040
A3: =SUM(A2,1) -> 2 | B3: XSS Injection Used to Hook Web-App Users' Browsers | C3: 40 | D3: 30 | E3: =_xlfn.CONCAT(OFFSET($A$1,ROW()-1,COLUMN()-3),OFFSET($A$1,ROW()-1,COLUMN()-2)) -> 4030
A4: =SUM(A3,1) -> 3 | B4: SQL Injection to Dump Web App Database | C4: 40 | D4: 40 | E4: =_xlfn.CONCAT(OFFSET($A$1,ROW()-1,COLUMN()-3),OFFSET($A$1,ROW()-1,COLUMN()-2)) -> 4040
A5: =SUM(A4,1) -> 4 | B5: Brute-force to login to user accounts | C5: 10 | D5: 20 | E5: =_xlfn.CONCAT(OFFSET($A$1,ROW()-1,COLUMN()-3),OFFSET($A$1,ROW()-1,COLUMN()-2)) -> 1020
A6: =SUM(A5,1) -> 5 | B6: XSS Injection Used to Hook Corporate Intranet Browsers | C6: 10 | D6: 30 | E6: =_xlfn.CONCAT(OFFSET($A$1,ROW()-1,COLUMN()-3),OFFSET($A$1,ROW()-1,COLUMN()-2)) -> 1030
A7: =SUM(A6,1) -> 6 | B7: Employee Steals FInancial Data from Physical Server | C7: 10 | D7: 10 | E7: =_xlfn.CONCAT(OFFSET($A$1,ROW()-1,COLUMN()-3),OFFSET($A$1,ROW()-1,COLUMN()-2)) -> 1010
A8: =SUM(A7,1) -> 7 | B8: Attacker Impersonates User in Financial Advisor Live Chat | C8: 10 | D8: 20 | E8: =_xlfn.CONCAT(OFFSET($A$1,ROW()-1,COLUMN()-3),OFFSET($A$1,ROW()-1,COLUMN()-2)) -> 1020
A9: =SUM(A8,1) -> 8 | B9: Employee Downloads Backdoor Into Corporate Intranet | C9: 10 | D9: 30 | E9: =_xlfn.CONCAT(OFFSET($A$1,ROW()-1,COLUMN()-3),OFFSET($A$1,ROW()-1,COLUMN()-2)) -> 1030
A10: =SUM(A9,1) -> 9 | B10: Finance Employee Downloads Backdoor Into Corporate Intranet | C10: 20 | D10: 30 | E10: =_xlfn.CONCAT(OFFSET($A$1,ROW()-1,COLUMN()-3),OFFSET($A$1,ROW()-1,COLUMN()-2)) -> 2030
F11: To add a new risk, drag the indicator in the bottom right corner of the right-most cell down, then edit as this will allocate a new riskID and autofill the helper column used to populate the Risk Matrix.

Sheet Risk Matrix
E1: LIKELIHOOD
E2: 10 Low | F2: 20 Medium | G2: 30 High | H2: 40 Very High
B3: IMPACT | C3: 10 | D3: Low | E3: =COUNTIF('Risk Assessment Data'!E:E, "1010") -> 1 | F3: =COUNTIF('Risk Assessment Data'!E:E, "2010") -> 0 | G3: =COUNTIF('Risk Assessment Data'!E:E, "3010") -> 0 | H3: =COUNTIF('Risk Assessment Data'!E:E, "4010") -> 0
C4: 20 | D4: Medium | E4: =COUNTIF('Risk Assessment Data'!E:E, "1020") -> 2 | F4: =COUNTIF('Risk Assessment Data'!E:E, "2020") -> 0 | G4: =COUNTIF('Risk Assessment Data'!E:E, "3020") -> 0 | H4: =COUNTIF('Risk Assessment Data'!E:E, "4020") -> 0
C5: 30 | D5: High | E5: =COUNTIF('Risk Assessment Data'!E:E, "1030") -> 2 | F5: =COUNTIF('Risk Assessment Data'!E:E, "2030") -> 1 | G5: =COUNTIF('Risk Assessment Data'!E:E, "3030") -> 0 | H5: =COUNTIF('Risk Assessment Data'!E:E, "4030") -> 1
C6: 40 | D6: Very High | E6: =COUNTIF('Risk Assessment Data'!E:E, "1040") -> 1 | F6: =COUNTIF('Risk Assessment Data'!E:E, "2040") -> 0 | G6: =COUNTIF('Risk Assessment Data'!E:E, "3040") -> 0 | H6: =COUNTIF('Risk Assessment Data'!E:E, "4040") -> 1
C7: Risk Matrix (autofilled from Risk Assessment Data) - shows the total number of identified risks per probability and impact per probability and impact score
E10: LIKELIHOOD
E11: 10 Low | F11: 20 Medium | G11: 30 High | H11: 40 Very High
B12: IMPACT | C12: 10 | D12: Low | E12: 5 | F12: 0 | G12: 0 | H12: 0
C13: 20 | D13: Medium | E13: 2 | F13: 0 | G13: 0 | H13: 0
C14: 30 | D14: High | E14: 2 | F14: 1 | G14: 0 | H14: 1
C15: 40 | D15: Very High | E15: 1 | F15: 0 | G15: 0 | H15: 1
C16: Sample Risk Matrix - an additional 4 risks but the risk profile is not overly dissimilar to above
E19: LIKELIHOOD
E20: 10 Low | F20: 20 Medium | G20: 30 High | H20: 40 Very High
B21: IMPACT | C21: 10 | D21: Low | E21: 1 | F21: 0 | G21: 0 | H21: 0
C22: 20 | D22: Medium | E22: 2 | F22: 0 | G22: 0 | H22: 0
C23: 30 | D23: High | E23: 2 | F23: 1 | G23: 0 | H23: 1
C24: 40 | D24: Very High | E24: 1 | F24: 0 | G24: 0 | H24: 5
C25: Another sample Risk Matrix - also an additional 4 risks, but a markedly different risk profile.

Sheet Heat Map
E1: LIKELIHOOD
E2: 10 | F2: 20 | G2: 30 | H2: 40
E3: Low | F3: Medium | G3: High | H3: Very High
B4: IMPACT | C4: 10 | D4: Low | E4: {=IFERROR(_xlfn.TEXTJOIN(", ",TRUE, _xlfn._xlws.FILTER(Risks[Risk ID],Risks[Likelihood-Impact]=_xlfn.CONCAT(E2,C4))),"")} -> 6 | F4: {=IFERROR(_xlfn.TEXTJOIN(", ",TRUE, _xlfn._xlws.FILTER(Risks[Risk ID],Risks[Likelihood-Impact]=_xlfn.CONCAT(F2,C4))),"")} | G4: {=IFERROR(_xlfn.TEXTJOIN(", ",TRUE, _xlfn._xlws.FILTER(Risks[Risk ID],Risks[Likelihood-Impact]=_xlfn.CONCAT(G2,C4))),"")} | H4: {=IFERROR(_xlfn.TEXTJOIN(", ",TRUE, _xlfn._xlws.FILTER(Risks[Risk ID],Risks[Likelihood-Impact]=_xlfn.CONCAT(H2,C4))),"")}
C5: 20 | D5: Medium | E5: {=IFERROR(_xlfn.TEXTJOIN(", ",TRUE, _xlfn._xlws.FILTER(Risks[Risk ID],Risks[Likelihood-Impact]=_xlfn.CONCAT(E2,C5))),"")} -> 4, 7 | F5: {=IFERROR(_xlfn.TEXTJOIN(", ",TRUE, _xlfn._xlws.FILTER(Risks[Risk ID],Risks[Likelihood-Impact]=_xlfn.CONCAT(F2,C5))),"")} | G5: {=IFERROR(_xlfn.TEXTJOIN(", ",TRUE, _xlfn._xlws.FILTER(Risks[Risk ID],Risks[Likelihood-Impact]=_xlfn.CONCAT(G2,C5))),"")} | H5: {=IFERROR(_xlfn.TEXTJOIN(", ",TRUE, _xlfn._xlws.FILTER(Risks[Risk ID],Risks[Likelihood-Impact]=_xlfn.CONCAT(H2,C5))),"")}
C6: 30 | D6: High | E6: {=IFERROR(_xlfn.TEXTJOIN(", ",TRUE, _xlfn._xlws.FILTER(Risks[Risk ID],Risks[Likelihood-Impact]=_xlfn.CONCAT(E2,C6))),"")} -> 5, 8 | F6: {=IFERROR(_xlfn.TEXTJOIN(", ",TRUE, _xlfn._xlws.FILTER(Risks[Risk ID],Risks[Likelihood-Impact]=_xlfn.CONCAT(F2,C6))),"")} -> 9 | G6: {=IFERROR(_xlfn.TEXTJOIN(", ",TRUE, _xlfn._xlws.FILTER(Risks[Risk ID],Risks[Likelihood-Impact]=_xlfn.CONCAT(G2,C6))),"")} | H6: {=IFERROR(_xlfn.TEXTJOIN(", ",TRUE, _xlfn._xlws.FILTER(Risks[Risk ID],Risks[Likelihood-Impact]=_xlfn.CONCAT(H2,C6))),"")} -> 2
C7: 40 | D7: Very High | E7: {=IFERROR(_xlfn.TEXTJOIN(", ",TRUE, _xlfn._xlws.FILTER(Risks[Risk ID],Risks[Likelihood-Impact]=_xlfn.CONCAT(E2,C7))),"")} -> 1 | F7: {=IFERROR(_xlfn.TEXTJOIN(", ",TRUE, _xlfn._xlws.FILTER(Risks[Risk ID],Risks[Likelihood-Impact]=_xlfn.CONCAT(F2,C7))),"")} | G7: {=IFERROR(_xlfn.TEXTJOIN(", ",TRUE, _xlfn._xlws.FILTER(Risks[Risk ID],Risks[Likelihood-Impact]=_xlfn.CONCAT(G2,C7))),"")} | H7: {=IFERROR(_xlfn.TEXTJOIN(", ",TRUE, _xlfn._xlws.FILTER(Risks[Risk ID],Risks[Likelihood-Impact]=_xlfn.CONCAT(H2,C7))),"")} -> 3
C8: Risk IDs by likelihood, impact

Sheet Risk Ratings
A1: GeldCorp
A2: Internal Risk Rating Guidelines
B4: LIKELIHOOD
B5: Score | C5: Description | D5: %
B6: 10 | C6: Rare: very small chance of happening | D6: 0.25 | G6: Likelihood assessment need not be based on probability - other possible factors include frequency of occurrence and complexity.
B7: 20 | C7: Unlikely: small chance of happening | D7: 0.5
B8: 30 | C8: Likely: Likely to happen | D8: 0.75
B9: 40 | C9: Expected: very high chance of happening or even certainty – this will happen | D9: 1
B11: IMPACT
B12: Score | C12: Description | D12: Monetary Impact
B13: 10 | C13: Minor impact. Negligible effect on the business's day-to-day operations and reputation. | D13: < $250k | G13: Impact assessment need not be based on direct financial impact - other possible factors include stakeholder relations and (legislative/regulatory) compliance.
B14: 20 | C14: Moderate impact. The incident will be expensive, but the company has enough cash to cover it. Day-to-day operations may slow, but will still continue. | D14: $250-$500k
B15: 30 | C15: High impact. The company has resources to address the breach, but may have to adjust budgets and project timelines to accommodate. Some day-ot-day operations will halt. | D15: $500k-$1M
B16: 40 | C16: Critical impact. The company's reputation and income are threatened. Responding to the incident may require the company to take out debt or sell assets. Reputational damage may be severe. | D16: < $1.1M

Sheet Risk Analysis Matrix
C1: Consequences
C2: 1. Insignificant | D2: 2. Minor | E2: 3. Moderate | F2: 4. Major | G2: 5. Catastrophic
A3: Likelihood | B3: 5. Almost Certain | C3: H | D3: H | E3: E | F3: E | G3: E | I3: E | K3: Extreme
B4: 4. Likely | C4: M | D4: H | E4: H | F4: E | G4: E | I4: H | K4: High
B5: 3. Possible | C5: L | D5: M | E5: H | F5: E | G5: E | I5: M | K5: Moderate
B6: 2. Unlikely | C6: L | D6: L | E6: M | F6: H | G6: E | I6: L | K6: Low
B7: 1. Rare | C7: L | D7: L | E7: M | F7: H | G7: H
B8: Eric Conrad, Seth Misenar, and Joshua Feldman, CISSP Study Guide, 2E (Syngress, 2012), 146
C10: Impact
C11: 1. Very Low | D11: 2. Low | E11: 3. Medium | F11: 4. High | G11: 5. Very High
A12: Probability | B12: 5. Very High | C12: 5 | D12: 10 | E12: 15 | F12: 20 | G12: 25
B13: 4. High | C13: 4 | D13: 8 | E13: 12 | F13: 16 | G13: 20 | I13: H | K13: High (>9)
B14: 3. Medium | C14: 3 | D14: 6 | E14: 9 | F14: 12 | G14: 15 | I14: M | K14: Moderate
B15: 2. Low | C15: 2 | D15: 4 | E15: 6 | F15: 8 | G15: 10 | I15: L | K15: Low (<5)
B16: 1. Very Low | C16: 1 | D16: 2 | E16: 3 | F16: 4 | G16: 5
B17: Tony Uceda Velez, and Marco M. Morena, Risk Centric Threat Modeling (Wiley, 2015), 266
C19: Impact
C20: 1. Very Low | D20: 2. Low | E20: 3. Medium | F20: 4. High | G20: 5. Very High
A21: Probability | B21: 5. Very High | C21: 5 | D21: 10 | E21: 15 | F21: 20 | G21: 25 | I21: E | K21: Extreme (>19)
B22: 4. High | C22: 4 | D22: 8 | E22: 12 | F22: 16 | G22: 20 | I22: H | K22: High (10 <= r <= 19)
B23: 3. Medium | C23: 3 | D23: 6 | E23: 9 | F23: 12 | G23: 15 | I23: M | K23: Moderate (5 <= r <= 9)
B24: 2. Low | C24: 2 | D24: 4 | E24: 6 | F24: 8 | G24: 10 | I24: L | K24: Low (r<5)
B25: 1. Very Low | C25: 1 | D25: 2 | E25: 3 | F25: 4 | G25: 5
B26: Variation on the Risk Analysis Matrix from Risk Centric Threat Modeling
C28: Impact
C29: 1. Very Low | D29: 2. Low | E29: 3. Medium | F29: 4. High | G29: 5. Very High
A30: Probability | B30: 5. Very High | C30: 5 | D30: 10 | E30: 15 | F30: 20 | G30: 25 | I30: E | K30: Extreme (>19)
B31: 4. High | C31: 4 | D31: 8 | E31: 12 | F31: 16 | G31: 20 | I31: H | K31: High (10 <= r <= 19)
B32: 3. Medium | C32: 3 | D32: 6 | E32: 9 | F32: 12 | G32: 15 | I32: M | K32: Moderate (5 <= r <= 9)
B33: 2. Low | C33: 2 | D33: 4 | E33: 6 | F33: 8 | G33: 10 | I33: L | K33: Low (2 <= r < 5)
B34: 1. Very Low | C34: 1 | D34: 2 | E34: 3 | F34: 4 | G34: 5 | I34: N | K34: Negligible (r = 1)
B35: Another variation on the Risk Analysis Matrix from Risk Centric Threat Modeling

Sheet MITRE probability descriptions
B1: MITRE Risk Management - Standard Process/Definitions: Probability of Occurrence
B3: Risk Event Probability | C3: Interpretation | D3: Rating
B4: > 0 - <= 0.05 | C4: Extremely sure not to occur | D4: Low
B5: > 0.05 - <= 0.15 | C5: Almost sure not to occur | D5: Low
B6: > 0.15 - <= 0.25 | C6: Not likely to occur | D6: Low
B7: > 0.25 - <= 0.35 | C7: Not very likely to occur | D7: Low
B8: > 0.35 - <= 0.45 | C8: Somewhat less than an even chance | D8: Medium
B9: > 0.45 - <= 0.55 | C9: An even chance to occur | D9: Medium
B10: > 0.55 - <= 0.65 | C10: Somewhat greater than an even chance | D10: Medium
B11: > 0.65 - <= 0.75 | C11: Likely to occur | D11: High
B12: > 0.75 - <= 0.85 | C12: Very likely to occur | D12: High
B13: > 0.85 - <= 0.95 | C13: Almost sure to occur | D13: High
B14: > 0.95 - < 1 | C14: Extremely sure to occur | D14: High
B16: http://www2.mitre.org/work/sepo/toolkits/risk/StandardProcess/definitions/occurence.html
